{
    "isTimeDim": false,
    "schemaName": "datainsight",
    "dimName": "Time",
    "dimTree": {
        "drillDown": false,
        "hasAll": false,
        "selected": false,
        "children": [
            {
                "drillDown": false,
                "hasAll": false,
                "selected": false,
                "children": [
                    {
                        "drillDown": false,
                        "hasAll": false,
                        "selected": false,
                        "name": "all$Time",
                        "uniqName": "all$[Time]",
                        "caption": "全部"
                    },
                    {
                        "drillDown": false,
                        "hasAll": false,
                        "selected": false,
                        "children": [
                            {
                                "drillDown": false,
                                "hasAll": false,
                                "selected": false,
                                "children": [
                                    {
                                        "drillDown": false,
                                        "hasAll": false,
                                        "selected": false,
                                        "name": "1",
                                        "uniqName": "[Time].[2012].[1].[1]",
                                        "caption": "1"
                                    }
                                ],
                                "name": "1",
                                "uniqName": "[Time].[2012].[1]",
                                "caption": "1"
                            }
                        ],
                        "name": "2012",
                        "uniqName": "[Time].[2012]",
                        "caption": "2012"
                    },
                    {
                        "drillDown": false,
                        "hasAll": false,
                        "selected": false,
                        "children": [
                            {
                                "drillDown": false,
                                "hasAll": false,
                                "selected": false,
                                "children": [
                                    {
                                        "drillDown": false,
                                        "hasAll": false,
                                        "selected": false,
                                        "name": "1",
                                        "uniqName": "[Time].[2013].[1].[1]",
                                        "caption": "1"
                                    }
                                ],
                                "name": "1",
                                "uniqName": "[Time].[2013].[1]",
                                "caption": "1"
                            }
                        ],
                        "name": "2013",
                        "uniqName": "[Time].[2013]",
                        "caption": "2013"
                    }
                ],
                "name": "Time",
                "uniqName": "[Time]",
                "caption": "Time"
            },
            {
                "drillDown": false,
                "hasAll": true,
                "selected": false,
                "children": [
                    {
                        "drillDown": false,
                        "hasAll": false,
                        "selected": false,
                        "name": "all$All Time.Weeklys",
                        "uniqName": "all$[Time.Weekly].[All Time.Weeklys]",
                        "caption": "全部"
                    },
                    {
                        "drillDown": false,
                        "hasAll": false,
                        "selected": false,
                        "children": [
                            {
                                "drillDown": false,
                                "hasAll": false,
                                "selected": false,
                                "children": [
                                    {
                                        "drillDown": false,
                                        "hasAll": false,
                                        "selected": false,
                                        "name": "7",
                                        "uniqName": "[Time.Weekly].[2012].[1].[7]",
                                        "caption": "7"
                                    }
                                ],
                                "name": "1",
                                "uniqName": "[Time.Weekly].[2012].[1]",
                                "caption": "1"
                            }
                        ],
                        "name": "2012",
                        "uniqName": "[Time.Weekly].[2012]",
                        "caption": "2012"
                    },
                    {
                        "drillDown": false,
                        "hasAll": false,
                        "selected": false,
                        "children": [
                            {
                                "drillDown": false,
                                "hasAll": false,
                                "selected": false,
                                "name": "all$2013",
                                "uniqName": "all$[Time.Weekly].[2013]",
                                "caption": "全部"
                            },
                            {
                                "drillDown": false,
                                "hasAll": false,
                                "selected": false,
                                "children": [
                                    {
                                        "drillDown": false,
                                        "hasAll": false,
                                        "selected": false,
                                        "name": "7",
                                        "uniqName": "[Time.Weekly].[2013].[1].[7]",
                                        "caption": "7"
                                    }
                                ],
                                "name": "1",
                                "uniqName": "[Time.Weekly].[2013].[1]",
                                "caption": "1"
                            },
                            {
                                "drillDown": false,
                                "hasAll": false,
                                "selected": false,
                                "children": [
                                    {
                                        "drillDown": false,
                                        "hasAll": false,
                                        "selected": false,
                                        "name": "14",
                                        "uniqName": "[Time.Weekly].[2013].[2].[14]",
                                        "caption": "14"
                                    }
                                ],
                                "name": "2",
                                "uniqName": "[Time.Weekly].[2013].[2]",
                                "caption": "2"
                            }
                        ],
                        "name": "2013",
                        "uniqName": "[Time.Weekly].[2013]",
                        "caption": "2013"
                    }
                ],
                "name": "Time.Weekly",
                "uniqName": "[Time.Weekly]",
                "caption": "Weekly"
            }
        ],
        "name": "Time",
        "uniqName": "[Time]",
        "caption": "Time"
    },
    "hierarchyLevelUniqueNames": {
        "Time": [
            {
                "name": "Year",
                "uniqName": "[Time].[Year]",
                "caption": "Year"
            },
            {
                "name": "Quarter",
                "uniqName": "[Time].[Quarter]",
                "caption": "Quarter"
            },
            {
                "name": "Month",
                "uniqName": "[Time].[Month]",
                "caption": "Month"
            }
        ],
        "Time.Weekly": [
            {
                "name": "Year",
                "uniqName": "[Time.Weekly].[Year]",
                "caption": "Year"
            },
            {
                "name": "Week",
                "uniqName": "[Time.Weekly].[Week]",
                "caption": "Week"
            },
            {
                "name": "Day",
                "uniqName": "[Time.Weekly].[Day]",
                "caption": "Day"
            }
        ]
    }
}